Metadata-Version: 2.1
Name: dask-pgen
Version: 0.1.1
Summary: Dask interface for memory-efficient reading PLINK genotype files
Home-page: https://github.com/kangchenghou/dask-pgen
Author: Kangcheng Hou
Author-email: kangchenghou@gmail.com
